<?xml version="1.0" encoding="utf-8"?><DEFECTS><DEFECT><SFA><FILEPATH>f:\c++\allegro\aced\staticdll\</FILEPATH><FILENAME>map.cpp</FILENAME><LINE>250</LINE><COLUMN>11</COLUMN></SFA><DEFECTCODE>6031</DEFECTCODE><DESCRIPTION>Return value ignored: 'strtok_s'.</DESCRIPTION><FUNCTION>StaticDLL::Map::loadMap</FUNCTION><DECORATED>?loadMap@Map@StaticDLL@@QAEXPAUALLEGRO_DISPLAY@@@Z</DECORATED><FUNCLINE>218</FUNCLINE><PATH /></DEFECT><DEFECT><SFA><FILEPATH>f:\c++\allegro\aced\staticdll\</FILEPATH><FILENAME>map.cpp</FILENAME><LINE>264</LINE><COLUMN>11</COLUMN></SFA><DEFECTCODE>6031</DEFECTCODE><DESCRIPTION>Return value ignored: 'strtok_s'.</DESCRIPTION><FUNCTION>StaticDLL::Map::loadMap</FUNCTION><DECORATED>?loadMap@Map@StaticDLL@@QAEXPAUALLEGRO_DISPLAY@@@Z</DECORATED><FUNCLINE>218</FUNCLINE><PATH /></DEFECT><DEFECT><SFA><FILEPATH>f:\c++\allegro\aced\staticdll\</FILEPATH><FILENAME>map.cpp</FILENAME><LINE>269</LINE><COLUMN>11</COLUMN></SFA><DEFECTCODE>6031</DEFECTCODE><DESCRIPTION>Return value ignored: 'strtok_s'.</DESCRIPTION><FUNCTION>StaticDLL::Map::loadMap</FUNCTION><DECORATED>?loadMap@Map@StaticDLL@@QAEXPAUALLEGRO_DISPLAY@@@Z</DECORATED><FUNCLINE>218</FUNCLINE><PATH /></DEFECT><DEFECT><SFA><FILEPATH>f:\c++\allegro\aced\staticdll\</FILEPATH><FILENAME>map.cpp</FILENAME><LINE>285</LINE><COLUMN>12</COLUMN></SFA><DEFECTCODE>6031</DEFECTCODE><DESCRIPTION>Return value ignored: 'strtok_s'.</DESCRIPTION><FUNCTION>StaticDLL::Map::loadMap</FUNCTION><DECORATED>?loadMap@Map@StaticDLL@@QAEXPAUALLEGRO_DISPLAY@@@Z</DECORATED><FUNCLINE>218</FUNCLINE><PATH /></DEFECT><DEFECT><SFA><FILEPATH>f:\c++\allegro\aced\staticdll\</FILEPATH><FILENAME>map.cpp</FILENAME><LINE>290</LINE><COLUMN>12</COLUMN></SFA><DEFECTCODE>6031</DEFECTCODE><DESCRIPTION>Return value ignored: 'strtok_s'.</DESCRIPTION><FUNCTION>StaticDLL::Map::loadMap</FUNCTION><DECORATED>?loadMap@Map@StaticDLL@@QAEXPAUALLEGRO_DISPLAY@@@Z</DECORATED><FUNCLINE>218</FUNCLINE><PATH /></DEFECT><DEFECT><SFA><FILEPATH>f:\c++\allegro\aced\staticdll\</FILEPATH><FILENAME>map.cpp</FILENAME><LINE>295</LINE><COLUMN>12</COLUMN></SFA><DEFECTCODE>6031</DEFECTCODE><DESCRIPTION>Return value ignored: 'strtok_s'.</DESCRIPTION><FUNCTION>StaticDLL::Map::loadMap</FUNCTION><DECORATED>?loadMap@Map@StaticDLL@@QAEXPAUALLEGRO_DISPLAY@@@Z</DECORATED><FUNCLINE>218</FUNCLINE><PATH /></DEFECT><DEFECT><SFA><FILEPATH>f:\c++\allegro\aced\staticdll\</FILEPATH><FILENAME>map.cpp</FILENAME><LINE>300</LINE><COLUMN>12</COLUMN></SFA><DEFECTCODE>6031</DEFECTCODE><DESCRIPTION>Return value ignored: 'strtok_s'.</DESCRIPTION><FUNCTION>StaticDLL::Map::loadMap</FUNCTION><DECORATED>?loadMap@Map@StaticDLL@@QAEXPAUALLEGRO_DISPLAY@@@Z</DECORATED><FUNCLINE>218</FUNCLINE><PATH /></DEFECT><DEFECT><SFA><FILEPATH>f:\c++\allegro\aced\staticdll\</FILEPATH><FILENAME>map.cpp</FILENAME><LINE>305</LINE><COLUMN>12</COLUMN></SFA><DEFECTCODE>6031</DEFECTCODE><DESCRIPTION>Return value ignored: 'strtok_s'.</DESCRIPTION><FUNCTION>StaticDLL::Map::loadMap</FUNCTION><DECORATED>?loadMap@Map@StaticDLL@@QAEXPAUALLEGRO_DISPLAY@@@Z</DECORATED><FUNCLINE>218</FUNCLINE><PATH /></DEFECT><DEFECT><SFA><FILEPATH>f:\c++\allegro\aced\staticdll\</FILEPATH><FILENAME>map.cpp</FILENAME><LINE>310</LINE><COLUMN>12</COLUMN></SFA><DEFECTCODE>6031</DEFECTCODE><DESCRIPTION>Return value ignored: 'strtok_s'.</DESCRIPTION><FUNCTION>StaticDLL::Map::loadMap</FUNCTION><DECORATED>?loadMap@Map@StaticDLL@@QAEXPAUALLEGRO_DISPLAY@@@Z</DECORATED><FUNCLINE>218</FUNCLINE><PATH /></DEFECT><DEFECT><SFA><FILEPATH>f:\c++\allegro\aced\staticdll\</FILEPATH><FILENAME>map.cpp</FILENAME><LINE>244</LINE><COLUMN>9</COLUMN></SFA><DEFECTCODE>6387</DEFECTCODE><DESCRIPTION>'_Param_(3)' could be '0':  this does not adhere to the specification for the function 'strtok_s'. </DESCRIPTION><FUNCTION>StaticDLL::Map::loadMap</FUNCTION><DECORATED>?loadMap@Map@StaticDLL@@QAEXPAUALLEGRO_DISPLAY@@@Z</DECORATED><FUNCLINE>218</FUNCLINE><PROBABILITY>1</PROBABILITY><RANK>4</RANK><CATEGORY><RULECATEGORY>mspft</RULECATEGORY></CATEGORY><PATH><SFA><FILEPATH>f:\c++\allegro\aced\staticdll\</FILEPATH><FILENAME>map.cpp</FILENAME><LINE>220</LINE><COLUMN>22</COLUMN></SFA><SFA><FILEPATH>f:\c++\allegro\aced\staticdll\</FILEPATH><FILENAME>map.cpp</FILENAME><LINE>221</LINE><COLUMN>14</COLUMN></SFA><SFA><FILEPATH>f:\c++\allegro\aced\staticdll\</FILEPATH><FILENAME>map.cpp</FILENAME><LINE>222</LINE><COLUMN>28</COLUMN></SFA><SFA><FILEPATH>f:\c++\allegro\aced\staticdll\</FILEPATH><FILENAME>map.cpp</FILENAME><LINE>224</LINE><COLUMN>6</COLUMN></SFA><SFA><FILEPATH>f:\c++\allegro\aced\staticdll\</FILEPATH><FILENAME>map.cpp</FILENAME><LINE>225</LINE><COLUMN>6</COLUMN></SFA><SFA><FILEPATH>f:\c++\allegro\aced\staticdll\</FILEPATH><FILENAME>map.cpp</FILENAME><LINE>227</LINE><COLUMN>14</COLUMN></SFA><SFA><FILEPATH>f:\c++\allegro\aced\staticdll\</FILEPATH><FILENAME>map.cpp</FILENAME><LINE>228</LINE><COLUMN>7</COLUMN></SFA><SFA><FILEPATH>f:\c++\allegro\aced\staticdll\</FILEPATH><FILENAME>map.cpp</FILENAME><LINE>230</LINE><COLUMN>10</COLUMN></SFA><SFA><FILEPATH>f:\c++\allegro\aced\staticdll\</FILEPATH><FILENAME>map.cpp</FILENAME><LINE>236</LINE><COLUMN>17</COLUMN></SFA><SFA><FILEPATH>f:\c++\allegro\aced\staticdll\</FILEPATH><FILENAME>map.cpp</FILENAME><LINE>237</LINE><COLUMN>6</COLUMN></SFA><SFA><FILEPATH>f:\c++\allegro\aced\staticdll\</FILEPATH><FILENAME>map.cpp</FILENAME><LINE>241</LINE><COLUMN>8</COLUMN></SFA><SFA><FILEPATH>f:\c++\allegro\aced\staticdll\</FILEPATH><FILENAME>map.cpp</FILENAME><LINE>243</LINE><COLUMN>11</COLUMN></SFA><SFA><FILEPATH>f:\c++\allegro\aced\staticdll\</FILEPATH><FILENAME>map.cpp</FILENAME><LINE>244</LINE><COLUMN>9</COLUMN></SFA></PATH></DEFECT></DEFECTS>